globaleaks_eph_fs/__init__.py
globaleaks_eph_fs/antani.py
globaleaks_eph_fs-0.0.3.dist-info/LICENSE
globaleaks_eph_fs-0.0.3.dist-info/METADATA
globaleaks_eph_fs-0.0.3.dist-info/WHEEL
globaleaks_eph_fs-0.0.3.dist-info/entry_points.txt
globaleaks_eph_fs-0.0.3.dist-info/top_level.txt
globaleaks_eph_fs-0.0.3.dist-info/RECORD
